gdp_tools/__init__.py
gdp_tools/lor_gdp_tools.py
gdp_tools/lor_llm_tools.py
gdp_tools/tests.py
lor_gdp_tools-1.2.8.dist-info/METADATA
lor_gdp_tools-1.2.8.dist-info/WHEEL
lor_gdp_tools-1.2.8.dist-info/top_level.txt
lor_gdp_tools-1.2.8.dist-info/RECORD
