Metadata-Version: 2.1
Name: lor_gdp_tools
Version: 1.2.8
Summary: This is a utility package designed to enable data scientitists and analysts to easily access GDP data within a python environment
Home-page: https://github.com/laingorourke/lor-gdp-tools
Author: Damian Rumble <DRumble@laingorourke.com>
